ckad_agent/__init__.py
ckad_agent/agent.py
ckad_agent/cli.py
ckad_agent/kubectl_tool.py
ckad_agent/models.py
ckad_agent/simple_debugger.py
ckad_agent-0.3.0.dist-info/METADATA
ckad_agent-0.3.0.dist-info/WHEEL
ckad_agent-0.3.0.dist-info/entry_points.txt
ckad_agent-0.3.0.dist-info/top_level.txt
ckad_agent-0.3.0.dist-info/RECORD
