Metadata-Version: 2.4
Name: ckad-agent
Version: 0.3.0
Summary: A CKAD (Certified Kubernetes Application Developer) exam preparation assistant
Author-email: Abdessslem Amri <amriabdesslem@gmail.com>
License: MIT
Classifier: Programming Language :: Python :: 3
Classifier: License :: OSI Approved :: MIT License
Classifier: Operating System :: OS Independent
Requires-Python: >=3.11
Requires-Dist: pydantic>=2.0.0
Requires-Dist: pydantic-ai>=0.8.0
Requires-Dist: python-dotenv>=1.0.0
Requires-Dist: kubernetes>=28.0.0
Requires-Dist: requests>=2.31.0
Requires-Dist: typer>=0.16.1
Provides-Extra: dev
Requires-Dist: pytest>=7.0.0; extra == "dev"
Requires-Dist: pytest-asyncio>=0.21.0; extra == "dev"
Requires-Dist: black>=23.0.0; extra == "dev"
Requires-Dist: isort>=5.12.0; extra == "dev"
Requires-Dist: mypy>=1.0.0; extra == "dev"
Requires-Dist: pylint>=3.0.0; extra == "dev"
Requires-Dist: pytest-cov>=4.0.0; extra == "dev"
